LICENSE
README.md
setup.py
wharfy/ActionBuild.py
wharfy/ActionConsole.py
wharfy/ActionRebuild.py
wharfy/ActionStart.py
wharfy/ActionStop.py
wharfy/Configfile.py
wharfy/FriendlyArgumentParser.py
wharfy/MultiCommand.py
wharfy/PrefixMatcher.py
wharfy/WorkDir.py
wharfy/__init__.py
wharfy/__main__.py
wharfy.egg-info/PKG-INFO
wharfy.egg-info/SOURCES.txt
wharfy.egg-info/dependency_links.txt
wharfy.egg-info/entry_points.txt
wharfy.egg-info/top_level.txt