Metadata-Version: 2.4
Name: wharfy
Version: 0.0.3
Summary: Tiny Docker orchestration toolkit without Yaml
Home-page: https://github.com/johndoe31415/wharfy
Download-URL: https://github.com/johndoe31415/wharfy/archive/v0.0.3.tar.gz
Author: Johannes Bauer
Author-email: joe@johannes-bauer.com
License: gpl-3.0
Keywords: docker,orchestration
Classifier: Development Status :: 4 - Beta
Classifier: Intended Audience :: Developers
Classifier: License :: OSI Approved :: GNU General Public License v3 (GPLv3)
Classifier: Programming Language :: Python :: 3
Classifier: Programming Language :: Python :: 3 :: Only
Classifier: Programming Language :: Python :: 3.12
Classifier: Programming Language :: Python :: 3.13
License-File: LICENSE
Dynamic: author
Dynamic: author-email
Dynamic: classifier
Dynamic: description
Dynamic: description-content-type
Dynamic: download-url
Dynamic: home-page
Dynamic: keywords
Dynamic: license
Dynamic: license-file
Dynamic: summary
